desim/__init__.py
desim/desim.py
desim_python-1.0.0.dist-info/licenses/LICENSE
desim_python-1.0.0.dist-info/METADATA
desim_python-1.0.0.dist-info/WHEEL
desim_python-1.0.0.dist-info/top_level.txt
desim_python-1.0.0.dist-info/RECORD
