Metadata-Version: 2.4
Name: desim-python
Version: 1.0.0
Summary: A Discrete Event Simulation (DES) library for modeling systems where state changes occur at discrete points in time.
Home-page: https://github.com/larias95/desim-python
Author: Luis Enrique Arias Curbelo
Author-email: lariasec@gmail.com
License: MIT License
Keywords: DES,discrete,event,queue,simulation,statistics
Classifier: Development Status :: 4 - Beta
Classifier: Intended Audience :: Developers
Classifier: Intended Audience :: Education
Classifier: Intended Audience :: Science/Research
Classifier: License :: OSI Approved :: MIT License
Classifier: Operating System :: OS Independent
Classifier: Programming Language :: Python
Classifier: Programming Language :: Python :: 3
Classifier: Topic :: Games/Entertainment :: Simulation
Classifier: Topic :: Scientific/Engineering
Classifier: Topic :: Scientific/Engineering :: Mathematics
License-File: LICENSE
Dynamic: author
Dynamic: author-email
Dynamic: classifier
Dynamic: description
Dynamic: description-content-type
Dynamic: home-page
Dynamic: keywords
Dynamic: license
Dynamic: license-file
Dynamic: summary
